PyPMT/PyPMT.py
PyPMT/__init__.py
PyPMT/data/SCAR_CGA_PLACE_NAMES.csv
PyPMT/data/__init__.py
PyPMT/data/moa2014_coastline_v01.dbf
PyPMT/data/moa2014_coastline_v01.evf
PyPMT/data/moa2014_coastline_v01.gmt
PyPMT/data/moa2014_coastline_v01.kml
PyPMT/data/moa2014_coastline_v01.prj
PyPMT/data/moa2014_coastline_v01.shp
PyPMT/data/moa2014_coastline_v01.shx
PyPMT/data/moa2014_coastline_v01.txt
PyPMT/data/moa2014_grounding_line_v01.dbf
PyPMT/data/moa2014_grounding_line_v01.evf
PyPMT/data/moa2014_grounding_line_v01.gmt
PyPMT/data/moa2014_grounding_line_v01.kml
PyPMT/data/moa2014_grounding_line_v01.prj
PyPMT/data/moa2014_grounding_line_v01.shp
PyPMT/data/moa2014_grounding_line_v01.shx
PyPMT/data/moa2014_grounding_line_v01.txt
PyPMT/data/moa2014_islands_v01.dbf
PyPMT/data/moa2014_islands_v01.evf
PyPMT/data/moa2014_islands_v01.gmt
PyPMT/data/moa2014_islands_v01.kml
PyPMT/data/moa2014_islands_v01.prj
PyPMT/data/moa2014_islands_v01.shp
PyPMT/data/moa2014_islands_v01.shx
PyPMT/data/moa2014_islands_v01.txt
PyPMT-1.1.1.dist-info/LICENSE
PyPMT-1.1.1.dist-info/METADATA
PyPMT-1.1.1.dist-info/WHEEL
PyPMT-1.1.1.dist-info/top_level.txt
PyPMT-1.1.1.dist-info/RECORD
