Metadata-Version: 2.2
Name: PyPMT
Version: 1.1.1
Summary: Python package for analysis and visualization of polar datasets.
Home-page: https://github.com/GatorGlaciology/PyPMT
Author: Blake Wood
Author-email: blakewood1@ufl.edu
License: MIT
Classifier: Programming Language :: Python :: 3
Classifier: License :: OSI Approved :: MIT License
Classifier: Operating System :: OS Independent
Classifier: Topic :: Scientific/Engineering :: Information Analysis
Requires-Python: >=3
License-File: LICENSE
Requires-Dist: Cartopy>=0.22.0
Requires-Dist: geopy>=2.3.0
Requires-Dist: matplotlib>=3.5.2
Requires-Dist: numpy>=2.0.1
Requires-Dist: pyproj>=3.5.0
Requires-Dist: scipy>=1.14.0
Requires-Dist: Shapely>=2.0.5
Requires-Dist: geopandas>=0.10.0
Requires-Dist: pathlib; python_version < "3.4"
Dynamic: author
Dynamic: author-email
Dynamic: classifier
Dynamic: description
Dynamic: description-content-type
Dynamic: home-page
Dynamic: license
Dynamic: requires-dist
Dynamic: requires-python
Dynamic: summary
